version.py
tmg_etl_library/__init__.py
tmg_etl_library/examples.py
tmg_etl_library/cloud_logger/__init__.py
tmg_etl_library/cloud_logger/cloud_logger.py
tmg_etl_library/components/__init__.py
tmg_etl_library/components/component.py
tmg_etl_library/components/config_classes.py
tmg_etl_library/components/buckets/__init__.py
tmg_etl_library/components/buckets/bucket.py
tmg_etl_library/components/buckets/ftp.py
tmg_etl_library/components/buckets/gs.py
tmg_etl_library/components/buckets/s3.py
tmg_etl_library/components/databases/__init__.py
tmg_etl_library/components/databases/bq.py
tmg_etl_library/components/databases/bt.py
tmg_etl_library/components/databases/database.py
tmg_etl_library/components/databases/mysql.py
tmg_etl_library/components/locals/__init__.py
tmg_etl_library/components/locals/csv.py
tmg_etl_library/components/locals/local.py
tmg_etl_library/components/queue/__init__.py
tmg_etl_library/components/queue/pubsub.py
tmg_etl_library/components/queue/queue.py
tmg_etl_library/data_transfers/__init__.py
tmg_etl_library/data_transfers/datatransfers.py
tmg_etl_library/data_transfers/transfer.py
tmg_etl_library/data_transfers/x_transfer.py
tmg_etl_library/threadpool/__init__.py
tmg_etl_library/threadpool/threadpool_manager.py
tmg_etl_library-1.1.0.dist-info/METADATA
tmg_etl_library-1.1.0.dist-info/WHEEL
tmg_etl_library-1.1.0.dist-info/top_level.txt
tmg_etl_library-1.1.0.dist-info/RECORD
