Metadata-Version: 2.1
Name: tmg-etl-library
Version: 1.1.0
Summary: TMG Etl library
Home-page: UNKNOWN
Author: Data Platform team
Author-email: UNKNOWN
License: UNKNOWN
Platform: UNKNOWN
Requires-Dist: boto3 (==1.9.87)
Requires-Dist: cachetools (==3.0.0)
Requires-Dist: certifi (==2018.11.29)
Requires-Dist: chardet (==3.0.4)
Requires-Dist: gcloud (==0.18.3)
Requires-Dist: google-api-core (==1.6.0)
Requires-Dist: google-api-python-client (==1.7.5)
Requires-Dist: google-auth (==1.6.1)
Requires-Dist: google-auth-httplib2 (==0.0.3)
Requires-Dist: google-cloud (==0.34.0)
Requires-Dist: google-cloud-bigquery (==1.7.0)
Requires-Dist: google-cloud-core (==0.28.1)
Requires-Dist: google-cloud-pubsub (==0.39.0)
Requires-Dist: google-cloud-storage (==1.13.0)
Requires-Dist: google-resumable-media (==0.3.1)
Requires-Dist: googleapis-common-protos (==1.5.5)
Requires-Dist: grpc-google-iam-v1 (==0.11.4)
Requires-Dist: grpcio (==1.17.0)
Requires-Dist: httplib2 (==0.12.0)
Requires-Dist: idna (==2.7)
Requires-Dist: jinja2 (==2.10)
Requires-Dist: jsonschema (==2.6.0)
Requires-Dist: mysql-connector (==2.1.6)
Requires-Dist: numpy (==1.15.4)
Requires-Dist: oauth2client (==4.1.3)
Requires-Dist: pandas (==0.23.4)
Requires-Dist: protobuf (==3.6.1)
Requires-Dist: pyasn1 (==0.4.4)
Requires-Dist: pyasn1-modules (==0.2.2)
Requires-Dist: pysftp (==0.2.9)
Requires-Dist: python-dateutil (==2.7.5)
Requires-Dist: pytz (==2018.7)
Requires-Dist: requests (==2.20.1)
Requires-Dist: rsa (==4.0)
Requires-Dist: six (==1.11.0)
Requires-Dist: sqlalchemy (==1.2.15)
Requires-Dist: uritemplate (==3.0.0)
Requires-Dist: urllib3 (==1.24.1)
